celux/__init__.py
celux/celux.pyd
celux/celux.pyi
celux_cuda-0.5.7.dist-info/METADATA
celux_cuda-0.5.7.dist-info/WHEEL
celux_cuda-0.5.7.dist-info/top_level.txt
celux_cuda-0.5.7.dist-info/RECORD
