Metadata-Version: 2.2
Name: celux-cuda
Version: 0.5.7
Summary: HW accelerated video reading for ML Inference (CUDA version).
Home-page: https://github.com/Trentonom0r3/celux
Author: Trenton Flanagan
Author-email: spigonvids@gmail.com
License: AGPL-3.0
Classifier: Programming Language :: Python :: 3
Classifier: License :: OSI Approved :: GNU Affero General Public License v3
Classifier: Operating System :: Microsoft :: Windows
Requires-Python: >=3.11
Dynamic: author
Dynamic: author-email
Dynamic: classifier
Dynamic: description
Dynamic: description-content-type
Dynamic: home-page
Dynamic: license
Dynamic: requires-python
Dynamic: summary
